{
  "indexes": [
    {
      "collectionGroup": "lessons",
      "queryScope": "COLLECTION",
      "fields": [
        {
          "fieldPath": "isOpen",
          "order": "ASCENDING"
        },
        {
          "fieldPath": "subject",
          "order": "ASCENDING"
        },
        {
          "fieldPath": "date",
          "order": "ASCENDING"
        }
      ]
    },
    {
      "collectionGroup": "lessons",
      "queryScope": "COLLECTION",
      "fields": [
        {
          "fieldPath": "students",
          "arrayConfig": "CONTAINS"
        },
        {
          "fieldPath": "date",
          "order": "ASCENDING"
        }
      ]
    },
    {
      "collectionGroup": "lessons",
      "queryScope": "COLLECTION",
      "fields": [
        {
          "fieldPath": "students",
          "arrayConfig": "CONTAINS"
        },
        {
          "fieldPath": "subject",
          "order": "ASCENDING"
        },
        {
          "fieldPath": "date",
          "order": "ASCENDING"
        }
      ]
    },
    {
      "collectionGroup": "lessons",
      "queryScope": "COLLECTION",
      "fields": [
        {
          "fieldPath": "tutor",
          "order": "ASCENDING"
        },
        {
          "fieldPath": "date",
          "order": "ASCENDING"
        }
      ]
    }
  ],
  "fieldOverrides": []
}
